purechainlib/__init__.py
purechainlib/account.py
purechainlib/carbon_tracker.py
purechainlib/carbon_tracker_v2.py
purechainlib/compiler.py
purechainlib/contract.py
purechainlib/direct_connection.py
purechainlib/exceptions.py
purechainlib/network.py
purechainlib/purechain.py
purechainlib/security_auditor.py
purechainlib/security_setup.py
purechainlib/web3_compat.py
purechainlib/utils/__init__.py
purechainlib/utils/performance.py
purechainlib-2.1.7.dist-info/LICENSE
purechainlib-2.1.7.dist-info/METADATA
purechainlib-2.1.7.dist-info/WHEEL
purechainlib-2.1.7.dist-info/entry_points.txt
purechainlib-2.1.7.dist-info/top_level.txt
purechainlib-2.1.7.dist-info/RECORD
