Metadata-Version: 2.1
Name: purechainlib
Version: 2.1.7
Summary: Python SDK for PureChain EVM network - Zero gas cost blockchain development
Home-page: https://pypi.org/project/purechainlib/
Author: PureChain Team
Author-email: dev@purechain.network
License: UNKNOWN
Project-URL: Documentation, https://docs.purechain.network
Project-URL: PyPI, https://pypi.org/project/purechainlib/
Project-URL: NPM Package, https://www.npmjs.com/package/purechainlib
Keywords: blockchain,ethereum,web3,smart-contracts,zero-gas,purechain,evm,solidity,defi,cryptocurrency,web3py,ethereum-development
Platform: UNKNOWN
Classifier: Development Status :: 5 - Production/Stable
Classifier: Intended Audience :: Developers
Classifier: License :: OSI Approved :: MIT License
Classifier: Operating System :: OS Independent
Classifier: Programming Language :: Python :: 3
Classifier: Programming Language :: Python :: 3.8
Classifier: Programming Language :: Python :: 3.9
Classifier: Programming Language :: Python :: 3.10
Classifier: Programming Language :: Python :: 3.11
Classifier: Programming Language :: Python :: 3.12
Classifier: Topic :: Software Development :: Libraries :: Python Modules
Classifier: Topic :: Internet :: WWW/HTTP
Classifier: Topic :: System :: Distributed Computing
Classifier: Topic :: Office/Business :: Financial
Classifier: Topic :: Security :: Cryptography
Requires-Python: >=3.8
License-File: LICENSE
Requires-Dist: eth-account (==0.10.0)
Requires-Dist: eth-utils (==2.3.1)
Requires-Dist: eth-abi (==4.0.0)
Requires-Dist: eth-hash (==0.7.0)
Requires-Dist: hexbytes (==0.3.1)
Requires-Dist: parsimonious (==0.9.0)
Requires-Dist: aiohttp (>=3.8.0)
Requires-Dist: jsonschema (>=4.0.0)
Requires-Dist: lru-dict (>=1.2.0)
Requires-Dist: protobuf (>=4.0.0)
Requires-Dist: pyunormalize (>=15.0.0)
Requires-Dist: requests (>=2.28.0)
Requires-Dist: typing-extensions (>=4.0.0)
Requires-Dist: websockets (>=11.0)
Requires-Dist: eth-typing (>=3.0.0)
Requires-Dist: eth-keys (>=0.4.0)
Requires-Dist: py-solc-x (==1.1.1)
Requires-Dist: semantic-version (==2.10.0)
Requires-Dist: httpx (==0.27.2)
Requires-Dist: aiofiles (==24.1.0)
Requires-Dist: ujson (==5.10.0)
Requires-Dist: coincurve (==19.0.1)
Requires-Dist: mnemonic (==0.21)
Requires-Dist: python-dotenv (==1.0.1)
Requires-Dist: pydantic (==2.9.2)
Requires-Dist: click (==8.1.7)
Requires-Dist: rich (==13.9.4)
Requires-Dist: slither-analyzer (==0.10.0)
Provides-Extra: dev
Requires-Dist: pytest (>=7.0.0) ; extra == 'dev'
Requires-Dist: pytest-asyncio (>=0.21.0) ; extra == 'dev'
Requires-Dist: pytest-cov (>=4.0.0) ; extra == 'dev'
Provides-Extra: web3
Requires-Dist: web3 (<7.0.0,>=6.20.0) ; extra == 'web3'
